{
  "kind": "youtube#commentThreadListResponse",
  "etag": "5yVM7aC-BjhutH4JhDRM-T8h_rI",
  "pageInfo": {
    "totalResults": 37,
    "resultsPerPage": 100
  },
  "items": [
    {
      "kind": "youtube#commentThread",
      "etag": "9VdrtraMQIMD-t3J0AQ6BifsCO4",
      "id": "UgzovpXxK23s38aCV6Z4AaABAg",
      "snippet": {
        "videoId": "-bjCeWG4YCg",
        "topLevelComment": {
          "kind": "youtube#comment",
          "etag": "IQTmc4IS-WLrHo0maQWZLEMRmN8",
          "id": "UgzovpXxK23s38aCV6Z4AaABAg",
          "snippet": {
            "videoId": "-bjCeWG4YCg",
            "textDisplay": "bitquits really? Just hand over Riley to have a chat",
            "textOriginal": "bitquits really? Just hand over Riley to have a chat",
            "authorDisplayName": "TheEnemy",
            "authorProfileImageUrl": "https://yt3.ggpht.com/ytc/AKedOLQEybLy0b5XeVpUMAEevYeKPuF9bYJqtY9zWg=s48-c-k-c0x00ffffff-no-rj",
            "authorChannelUrl": "http://www.youtube.com/channel/UCEf1GCo7nOMnH-T_y8hhK7A",
            "authorChannelId": {
              "value": "UCEf1GCo7nOMnH-T_y8hhK7A"
            },
            "canRate": true,
            "viewerRating": "none",
            "likeCount": 0,
            "publishedAt": "2018-06-19T00:38:58Z",
            "updatedAt": "2018-06-19T00:38:58Z"
          }
        },
        "canReply": true,
        "totalReplyCount": 0,
        "isPublic": true
      }
    },
    {
      "kind": "youtube#commentThread",
      "etag": "txZGqWYtkIILKN0Koc1OxWvEq3o",
      "id": "UgwFj2zGDRcIcRnOpKl4AaABAg",
      "snippet": {
        "videoId": "-bjCeWG4YCg",
        "topLevelComment": {
          "kind": "youtube#comment",
          "etag": "n26AZNVi9ilL-w8M8eLcf0jT9Ag",
          "id": "UgwFj2zGDRcIcRnOpKl4AaABAg",
          "snippet": {
            "videoId": "-bjCeWG4YCg",
            "textDisplay": "AMD giveaway is only available on the US and Intel giveaway is only available on 9 countries. Both SUCK.",
            "textOriginal": "AMD giveaway is only available on the US and Intel giveaway is only available on 9 countries. Both SUCK.",
            "authorDisplayName": "Angelo Batista do Nascimento",
            "authorProfileImageUrl": "https://yt3.ggpht.com/ytc/AKedOLQE-oPzEtoRWY00jxu3F_ElCGsuU3Rpiv9aqmK6tg=s48-c-k-c0x00ffffff-no-rj",
            "authorChannelUrl": "http://www.youtube.com/channel/UCFZ9WsQDsjrFCH_nA7DQunA",
            "authorChannelId": {
              "value": "UCFZ9WsQDsjrFCH_nA7DQunA"
            },
            "canRate": true,
            "viewerRating": "none",
            "likeCount": 0,
            "publishedAt": "2018-06-19T00:38:35Z",
            "updatedAt": "2018-06-19T00:38:35Z"
          }
        },
        "canReply": true,
        "totalReplyCount": 0,
        "isPublic": true
      }
    },
    {
      "kind": "youtube#commentThread",
      "etag": "peJU3UC8lGD5iC0JsR99-9Rwy2c",
      "id": "UgwAsEkTpaMxn0dKfKp4AaABAg",
      "snippet": {
        "videoId": "-bjCeWG4YCg",
        "topLevelComment": {
          "kind": "youtube#comment",
          "etag": "Djpp_Y8J05O_RzcZmC503IH2lKA",
          "id": "UgwAsEkTpaMxn0dKfKp4AaABAg",
          "snippet": {
            "videoId": "-bjCeWG4YCg",
            "textDisplay": "lol AMD",
            "textOriginal": "lol AMD",
            "authorDisplayName": "Jetfire",
            "authorProfileImageUrl": "https://yt3.ggpht.com/ytc/AKedOLS-swCrWop3cFcFx50C8L6ZOVfYtGAiU1ixERm-=s48-c-k-c0x00ffffff-no-rj",
            "authorChannelUrl": "http://www.youtube.com/channel/UCAD_1nLPEG0qkgfJ3nq29Pw",
            "authorChannelId": {
              "value": "UCAD_1nLPEG0qkgfJ3nq29Pw"
            },
            "canRate": true,
            "viewerRating": "none",
            "likeCount": 0,
            "publishedAt": "2018-06-19T00:38:31Z",
            "updatedAt": "2018-06-19T00:38:31Z"
          }
        },
        "canReply": true,
        "totalReplyCount": 1,
        "isPublic": true
      }
    },
    {
      "kind": "youtube#commentThread",
      "etag": "s3pO755OZgU8hnXWKPB__xQo5vE",
      "id": "Ugy4hRM8zM_vy-ycvF14AaABAg",
      "snippet": {
        "videoId": "-bjCeWG4YCg",
        "topLevelComment": {
          "kind": "youtube#comment",
          "etag": "QkKVC_N0sGlpj1aCicR4UEZW_Ws",
          "id": "Ugy4hRM8zM_vy-ycvF14AaABAg",
          "snippet": {
            "videoId": "-bjCeWG4YCg",
            "textDisplay": "Yes now YouTube red works in Mexico, that really pissed me off when I went in January",
            "textOriginal": "Yes now YouTube red works in Mexico, that really pissed me off when I went in January",
            "authorDisplayName": "Jose Brito",
            "authorProfileImageUrl": "https://yt3.ggpht.com/ytc/AKedOLRbfysKsi27i8K666vphNsTABwRuvadIgkq9Xk1gzs=s48-c-k-c0x00ffffff-no-rj",
            "authorChannelUrl": "http://www.youtube.com/channel/UCRGVE6UsRUOVthlQ3ADoD8g",
            "authorChannelId": {
              "value": "UCRGVE6UsRUOVthlQ3ADoD8g"
            },
            "canRate": true,
            "viewerRating": "none",
            "likeCount": 0,
            "publishedAt": "2018-06-19T00:37:40Z",
            "updatedAt": "2018-06-19T00:37:40Z"
          }
        },
        "canReply": true,
        "totalReplyCount": 0,
        "isPublic": true
      }
    },
    {
      "kind": "youtube#commentThread",
      "etag": "TEtvZw1fba0LUReFpX4AWn5GrXI",
      "id": "Ugyc_HZeGgRM0yX5ixt4AaABAg",
      "snippet": {
        "videoId": "-bjCeWG4YCg",
        "topLevelComment": {
          "kind": "youtube#comment",
          "etag": "mxEsG8ATIU3fvEH9qyB8AuX44pA",
          "id": "Ugyc_HZeGgRM0yX5ixt4AaABAg",
          "snippet": {
            "videoId": "-bjCeWG4YCg",
            "textDisplay": "mfw AMD has become SEGA marketing on steroids",
            "textOriginal": "mfw AMD has become SEGA marketing on steroids",
            "authorDisplayName": "Deanchimp",
            "authorProfileImageUrl": "https://yt3.ggpht.com/ytc/AKedOLR32hnjKrMNJit1HC4Ij4wrA6dyw50FaTRaQQ=s48-c-k-c0x00ffffff-no-rj",
            "authorChannelUrl": "http://www.youtube.com/channel/UCHhzKufNQs4DIWYuF1epCRw",
            "authorChannelId": {
              "value": "UCHhzKufNQs4DIWYuF1epCRw"
            },
            "canRate": true,
            "viewerRating": "none",
            "likeCount": 92,
            "publishedAt": "2018-06-19T00:36:46Z",
            "updatedAt": "2018-06-19T00:36:46Z"
          }
        },
        "canReply": true,
        "totalReplyCount": 8,
        "isPublic": true
      }
    },
    {
      "kind": "youtube#commentThread",
      "etag": "zIRik15tskLPvMTlEENfW2SbWaM",
      "id": "UgzSDRx-3j8TAAoC5qR4AaABAg",
      "snippet": {
        "videoId": "-bjCeWG4YCg",
        "topLevelComment": {
          "kind": "youtube#comment",
          "etag": "mew9OGdTlHVJYj39ZyZgZ2swZ4k",
          "id": "UgzSDRx-3j8TAAoC5qR4AaABAg",
          "snippet": {
            "videoId": "-bjCeWG4YCg",
            "textDisplay": "I am the 5th person to view this video!!\nXD",
            "textOriginal": "I am the 5th person to view this video!!\nXD",
            "authorDisplayName": "Sanjeev Mohan",
            "authorProfileImageUrl": "https://yt3.ggpht.com/ytc/AKedOLQ_qpZ5-EuIepkUIxha3qtsWsJRbhEppXJoQEGD274=s48-c-k-c0x00ffffff-no-rj",
            "authorChannelUrl": "http://www.youtube.com/channel/UCvTScGecRPnkefMzL8Ln5bA",
            "authorChannelId": {
              "value": "UCvTScGecRPnkefMzL8Ln5bA"
            },
            "canRate": true,
            "viewerRating": "none",
            "likeCount": 0,
            "publishedAt": "2018-06-19T00:36:27Z",
            "updatedAt": "2018-06-19T00:36:27Z"
          }
        },
        "canReply": true,
        "totalReplyCount": 1,
        "isPublic": true
      }
    },
    {
      "kind": "youtube#commentThread",
      "etag": "XYeqoBSnZwZrfyKcuaYyIpCht7s",
      "id": "UgxoSD4oAr2zMZro3VR4AaABAg",
      "snippet": {
        "videoId": "-bjCeWG4YCg",
        "topLevelComment": {
          "kind": "youtube#comment",
          "etag": "nJpUuVhyLO5PDvpvyj-4OT9aNQY",
          "id": "UgxoSD4oAr2zMZro3VR4AaABAg",
          "snippet": {
            "videoId": "-bjCeWG4YCg",
            "textDisplay": "AMD FOR THE WIN ^^",
            "textOriginal": "AMD FOR THE WIN ^^",
            "authorDisplayName": "Francisco Santos",
            "authorProfileImageUrl": "https://yt3.ggpht.com/ytc/AKedOLQfhZZAXwvz5JLYe21yIrBtZDJm49zHVxEvgmmU8w=s48-c-k-c0x00ffffff-no-rj",
            "authorChannelUrl": "http://www.youtube.com/channel/UC_JLyyBgosLfjjqxFoJC2DQ",
            "authorChannelId": {
              "value": "UC_JLyyBgosLfjjqxFoJC2DQ"
            },
            "canRate": true,
            "viewerRating": "none",
            "likeCount": 13,
            "publishedAt": "2018-06-19T00:36:05Z",
            "updatedAt": "2018-06-19T00:36:05Z"
          }
        },
        "canReply": true,
        "totalReplyCount": 12,
        "isPublic": true
      }
    },
    {
      "kind": "youtube#commentThread",
      "etag": "RhovzLTIEZgtR0TNuqexH5XV8PU",
      "id": "UgyK5gmjauRT9y_HpZ14AaABAg",
      "snippet": {
        "videoId": "-bjCeWG4YCg",
        "topLevelComment": {
          "kind": "youtube#comment",
          "etag": "pA7biCi3m6-F9oZ5yH8Lct6WE-o",
          "id": "UgyK5gmjauRT9y_HpZ14AaABAg",
          "snippet": {
            "videoId": "-bjCeWG4YCg",
            "textDisplay": "I agree, Linus, they do suck.",
            "textOriginal": "I agree, Linus, they do suck.",
            "authorDisplayName": "RemixedMelody",
            "authorProfileImageUrl": "https://yt3.ggpht.com/ytc/AKedOLRuJ22AgGcMXW2x-Na03BQ7Xg7lDGl3Wx9fa3tZ=s48-c-k-c0x00ffffff-no-rj",
            "authorChannelUrl": "http://www.youtube.com/channel/UC31OHxc3wyUv-DsyY_NggLQ",
            "authorChannelId": {
              "value": "UC31OHxc3wyUv-DsyY_NggLQ"
            },
            "canRate": true,
            "viewerRating": "none",
            "likeCount": 2,
            "publishedAt": "2018-06-19T00:35:53Z",
            "updatedAt": "2018-06-19T00:35:53Z"
          }
        },
        "canReply": true,
        "totalReplyCount": 0,
        "isPublic": true
      }
    },
    {
      "kind": "youtube#commentThread",
      "etag": "Sw8FzAdC9TaJzZeIfcF4X9OjU2Y",
      "id": "UgzlIdQTB297k3yLJ014AaABAg",
      "snippet": {
        "videoId": "-bjCeWG4YCg",
        "topLevelComment": {
          "kind": "youtube#comment",
          "etag": "hF4ZR0YOOIJr_zF0VaqfTJi4rYA",
          "id": "UgzlIdQTB297k3yLJ014AaABAg",
          "snippet": {
            "videoId": "-bjCeWG4YCg",
            "textDisplay": "i hope Intel goes bankrupt",
            "textOriginal": "i hope Intel goes bankrupt",
            "authorDisplayName": "Xtard Destroyer",
            "authorProfileImageUrl": "https://yt3.ggpht.com/ytc/AKedOLSHVi-iE2c6UsMF3_EDGq7pSaHz9uBSru9Ug7kU6g=s48-c-k-c0x00ffffff-no-rj",
            "authorChannelUrl": "http://www.youtube.com/channel/UCAAw27xmsAxXb_ExjwbI-TA",
            "authorChannelId": {
              "value": "UCAAw27xmsAxXb_ExjwbI-TA"
            },
            "canRate": true,
            "viewerRating": "none",
            "likeCount": 0,
            "publishedAt": "2018-06-19T00:35:44Z",
            "updatedAt": "2018-06-19T00:35:44Z"
          }
        },
        "canReply": true,
        "totalReplyCount": 3,
        "isPublic": true
      }
    },
    {
      "kind": "youtube#commentThread",
      "etag": "TN5V7zpGdIWkybAoYh_D04hu2uA",
      "id": "UgwuKKzVT4KyH7gT_9Z4AaABAg",
      "snippet": {
        "videoId": "-bjCeWG4YCg",
        "topLevelComment": {
          "kind": "youtube#comment",
          "etag": "XZBYxdq2sYxl05DVECccmvLT8rg",
          "id": "UgwuKKzVT4KyH7gT_9Z4AaABAg",
          "snippet": {
            "videoId": "-bjCeWG4YCg",
            "textDisplay": "RIP INTEL 2018",
            "textOriginal": "RIP INTEL 2018",
            "authorDisplayName": "Francisco Santos",
            "authorProfileImageUrl": "https://yt3.ggpht.com/ytc/AKedOLQfhZZAXwvz5JLYe21yIrBtZDJm49zHVxEvgmmU8w=s48-c-k-c0x00ffffff-no-rj",
            "authorChannelUrl": "http://www.youtube.com/channel/UC_JLyyBgosLfjjqxFoJC2DQ",
            "authorChannelId": {
              "value": "UC_JLyyBgosLfjjqxFoJC2DQ"
            },
            "canRate": true,
            "viewerRating": "none",
            "likeCount": 8,
            "publishedAt": "2018-06-19T00:35:38Z",
            "updatedAt": "2018-06-19T00:35:38Z"
          }
        },
        "canReply": true,
        "totalReplyCount": 0,
        "isPublic": true
      }
    },
    {
      "kind": "youtube#commentThread",
      "etag": "oMRgKtekHZ5-SaU39qEOfbCedfE",
      "id": "UgzOAgn1XIpxkY-D86B4AaABAg",
      "snippet": {
        "videoId": "-bjCeWG4YCg",
        "topLevelComment": {
          "kind": "youtube#comment",
          "etag": "ljGdV9wlgeQdA9RMMuZGSMSSBd0",
          "id": "UgzOAgn1XIpxkY-D86B4AaABAg",
          "snippet": {
            "videoId": "-bjCeWG4YCg",
            "textDisplay": "Neat",
            "textOriginal": "Neat",
            "authorDisplayName": "Viciouz Ascend",
            "authorProfileImageUrl": "https://yt3.ggpht.com/ytc/AKedOLQBIwvx3m6KfqpuP-1w7itjn_SxypD4DcVQByFs=s48-c-k-c0x00ffffff-no-rj",
            "authorChannelUrl": "http://www.youtube.com/channel/UCSLzDoOBSGNyk8OdSc1D1Eg",
            "authorChannelId": {
              "value": "UCSLzDoOBSGNyk8OdSc1D1Eg"
            },
            "canRate": true,
            "viewerRating": "none",
            "likeCount": 0,
            "publishedAt": "2018-06-19T00:34:43Z",
            "updatedAt": "2018-06-19T00:34:43Z"
          }
        },
        "canReply": true,
        "totalReplyCount": 0,
        "isPublic": true
      }
    },
    {
      "kind": "youtube#commentThread",
      "etag": "lW0uiCszSCUGT4LQUCQ0j8BpR3k",
      "id": "UgyS5jxkJcPhFE4nU0t4AaABAg",
      "snippet": {
        "videoId": "-bjCeWG4YCg",
        "topLevelComment": {
          "kind": "youtube#comment",
          "etag": "OXS_4w-cmqecBpCD_K5_SvQkDg4",
          "id": "UgyS5jxkJcPhFE4nU0t4AaABAg",
          "snippet": {
            "videoId": "-bjCeWG4YCg",
            "textDisplay": "25th viewer",
            "textOriginal": "25th viewer",
            "authorDisplayName": "Andrew's Nerdiness!!",
            "authorProfileImageUrl": "https://yt3.ggpht.com/ytc/AKedOLRaa9KjQwCCZpMUSWaBsZOKEDYCHaw88WzrsLoH=s48-c-k-c0x00ffffff-no-rj",
            "authorChannelUrl": "http://www.youtube.com/channel/UCxRaINsbGo227Fj1Ee-wzUw",
            "authorChannelId": {
              "value": "UCxRaINsbGo227Fj1Ee-wzUw"
            },
            "canRate": true,
            "viewerRating": "none",
            "likeCount": 0,
            "publishedAt": "2018-06-19T00:34:36Z",
            "updatedAt": "2018-06-19T00:34:36Z"
          }
        },
        "canReply": true,
        "totalReplyCount": 0,
        "isPublic": true
      }
    },
    {
      "kind": "youtube#commentThread",
      "etag": "5pZiTxnya_KEvYy2J0ijbADGbXU",
      "id": "UgxbRcsfeYFil3ogB6J4AaABAg",
      "snippet": {
        "videoId": "-bjCeWG4YCg",
        "topLevelComment": {
          "kind": "youtube#comment",
          "etag": "AiSzNlr93KoN7cDUTKd9diSl8l8",
          "id": "UgxbRcsfeYFil3ogB6J4AaABAg",
          "snippet": {
            "videoId": "-bjCeWG4YCg",
            "textDisplay": "and here i am with my old but still perfectly working and not overheating fx6300 my 1st love!\nbtw not changing it until it dies!",
            "textOriginal": "and here i am with my old but still perfectly working and not overheating fx6300 my 1st love!\nbtw not changing it until it dies!",
            "authorDisplayName": "Lord Toshibakoludo",
            "authorProfileImageUrl": "https://yt3.ggpht.com/ytc/AKedOLRwmFq26UNTa3YHv23IsgllcndU7n5SCDaOLe18EA=s48-c-k-c0x00ffffff-no-rj",
            "authorChannelUrl": "http://www.youtube.com/channel/UCGN3nD4KMUWndSbQFiz99AQ",
            "authorChannelId": {
              "value": "UCGN3nD4KMUWndSbQFiz99AQ"
            },
            "canRate": true,
            "viewerRating": "none",
            "likeCount": 2,
            "publishedAt": "2018-06-19T00:34:18Z",
            "updatedAt": "2018-06-19T00:39:04Z"
          }
        },
        "canReply": true,
        "totalReplyCount": 5,
        "isPublic": true
      }
    },
    {
      "kind": "youtube#commentThread",
      "etag": "ABjn3Q8QMpcMIJn2kcAZeZL_rUU",
      "id": "UgwEihCneH_pYBQEYd54AaABAg",
      "snippet": {
        "videoId": "-bjCeWG4YCg",
        "topLevelComment": {
          "kind": "youtube#comment",
          "etag": "EENrJMHuqgtvWqU-zZLsxc-D3uw",
          "id": "UgwEihCneH_pYBQEYd54AaABAg",
          "snippet": {
            "videoId": "-bjCeWG4YCg",
            "textDisplay": "I would get youtube music but I get spotify for free",
            "textOriginal": "I would get youtube music but I get spotify for free",
            "authorDisplayName": "Marc Anderson",
            "authorProfileImageUrl": "https://yt3.ggpht.com/ytc/AKedOLQR-YEePPV4rUmSyPPapkhUjgq9d7A0gl95fKDHjQ=s48-c-k-c0x00ffffff-no-rj",
            "authorChannelUrl": "http://www.youtube.com/channel/UCxTy6LXyWL4OSOXC1ZwTuWg",
            "authorChannelId": {
              "value": "UCxTy6LXyWL4OSOXC1ZwTuWg"
            },
            "canRate": true,
            "viewerRating": "none",
            "likeCount": 0,
            "publishedAt": "2018-06-19T00:33:54Z",
            "updatedAt": "2018-06-19T00:33:54Z"
          }
        },
        "canReply": true,
        "totalReplyCount": 0,
        "isPublic": true
      }
    },
    {
      "kind": "youtube#commentThread",
      "etag": "Q82sAQU0re7kCdZvrnPceySobFQ",
      "id": "UgxmODTIimjbFFgYW-N4AaABAg",
      "snippet": {
        "videoId": "-bjCeWG4YCg",
        "topLevelComment": {
          "kind": "youtube#comment",
          "etag": "DMEhXHYrLyOd6RpUKVogLIyh0vk",
          "id": "UgxmODTIimjbFFgYW-N4AaABAg",
          "snippet": {
            "videoId": "-bjCeWG4YCg",
            "textDisplay": "Damn. That AMD burn on Intel is pretty sick. XD",
            "textOriginal": "Damn. That AMD burn on Intel is pretty sick. XD",
            "authorDisplayName": "Dominic Francis",
            "authorProfileImageUrl": "https://yt3.ggpht.com/ytc/AKedOLQ3vd90pF7MHxGrb3gsG5EePVjkIDT-LB0r3cS3=s48-c-k-c0x00ffffff-no-rj",
            "authorChannelUrl": "http://www.youtube.com/channel/UC-tAeRsAv59YfYud6TXAbOw",
            "authorChannelId": {
              "value": "UC-tAeRsAv59YfYud6TXAbOw"
            },
            "canRate": true,
            "viewerRating": "none",
            "likeCount": 373,
            "publishedAt": "2018-06-19T00:33:22Z",
            "updatedAt": "2018-06-19T00:33:22Z"
          }
        },
        "canReply": true,
        "totalReplyCount": 47,
        "isPublic": true
      }
    },
    {
      "kind": "youtube#commentThread",
      "etag": "BRR7GDRxaYG_ILsz1u6aaRoeMRA",
      "id": "Ugx7bOl1Ot0XVkz4Z7d4AaABAg",
      "snippet": {
        "videoId": "-bjCeWG4YCg",
        "topLevelComment": {
          "kind": "youtube#comment",
          "etag": "Sef2ZCQnnqpXOataVuYqxjhUy0g",
          "id": "Ugx7bOl1Ot0XVkz4Z7d4AaABAg",
          "snippet": {
            "videoId": "-bjCeWG4YCg",
            "textDisplay": "25th view",
            "textOriginal": "25th view",
            "authorDisplayName": "Alex Nicolazzo",
            "authorProfileImageUrl": "https://yt3.ggpht.com/ytc/AKedOLSKzz0If0jzj2yZhTaBbbpik_tRvUBz5luyEJSWvQ=s48-c-k-c0x00ffffff-no-rj",
            "authorChannelUrl": "http://www.youtube.com/channel/UCSUgxsGczgnXOWTL_XB64sw",
            "authorChannelId": {
              "value": "UCSUgxsGczgnXOWTL_XB64sw"
            },
            "canRate": true,
            "viewerRating": "none",
            "likeCount": 0,
            "publishedAt": "2018-06-19T00:33:06Z",
            "updatedAt": "2018-06-19T00:33:06Z"
          }
        },
        "canReply": true,
        "totalReplyCount": 0,
        "isPublic": true
      }
    },
    {
      "kind": "youtube#commentThread",
      "etag": "S4SlbGvtZiQtGkZRgHdLRRNn9Sw",
      "id": "UgxXR08UQpZTPIi1pNh4AaABAg",
      "snippet": {
        "videoId": "-bjCeWG4YCg",
        "topLevelComment": {
          "kind": "youtube#comment",
          "etag": "b1x3553M4G3l75lx-Qo4qfi_jEE",
          "id": "UgxXR08UQpZTPIi1pNh4AaABAg",
          "snippet": {
            "videoId": "-bjCeWG4YCg",
            "textDisplay": "26th :)",
            "textOriginal": "26th :)",
            "authorDisplayName": "David Dunlop",
            "authorProfileImageUrl": "https://yt3.ggpht.com/ytc/AKedOLTC0l08fYktR76oYDEaP3EjsPzwm01pOOoMhZAjbg=s48-c-k-c0x00ffffff-no-rj",
            "authorChannelUrl": "http://www.youtube.com/channel/UC0v--glANulFc1B-jc1PZug",
            "authorChannelId": {
              "value": "UC0v--glANulFc1B-jc1PZug"
            },
            "canRate": true,
            "viewerRating": "none",
            "likeCount": 0,
            "publishedAt": "2018-06-19T00:32:56Z",
            "updatedAt": "2018-06-19T00:32:56Z"
          }
        },
        "canReply": true,
        "totalReplyCount": 0,
        "isPublic": true
      }
    },
    {
      "kind": "youtube#commentThread",
      "etag": "32-I_2wrhLRHc8Yp21poqZ1bi2E",
      "id": "UgxTPGsuzrXwUNryrvZ4AaABAg",
      "snippet": {
        "videoId": "-bjCeWG4YCg",
        "topLevelComment": {
          "kind": "youtube#comment",
          "etag": "Mxl05CiiWnMfez4_yPCv-Ik--ME",
          "id": "UgxTPGsuzrXwUNryrvZ4AaABAg",
          "snippet": {
            "videoId": "-bjCeWG4YCg",
            "textDisplay": "under 50 views... yeet",
            "textOriginal": "under 50 views... yeet",
            "authorDisplayName": "MATT",
            "authorProfileImageUrl": "https://yt3.ggpht.com/ytc/AKedOLRVz0CqSm6S67o9cGfZ83PHbcw-JxMoBS-BMmiiSQ=s48-c-k-c0x00ffffff-no-rj",
            "authorChannelUrl": "http://www.youtube.com/channel/UCmicmqk9pjdOpgsTfg-FNow",
            "authorChannelId": {
              "value": "UCmicmqk9pjdOpgsTfg-FNow"
            },
            "canRate": true,
            "viewerRating": "none",
            "likeCount": 0,
            "publishedAt": "2018-06-19T00:32:50Z",
            "updatedAt": "2018-06-19T00:32:50Z"
          }
        },
        "canReply": true,
        "totalReplyCount": 0,
        "isPublic": true
      }
    },
    {
      "kind": "youtube#commentThread",
      "etag": "IdVBSa833P8nLHEf8hOiXLaBHp8",
      "id": "Ugz4GFlf1tq8DKfPTH14AaABAg",
      "snippet": {
        "videoId": "-bjCeWG4YCg",
        "topLevelComment": {
          "kind": "youtube#comment",
          "etag": "0XB3geGZYeFN-MpwArUtlqITqUM",
          "id": "Ugz4GFlf1tq8DKfPTH14AaABAg",
          "snippet": {
            "videoId": "-bjCeWG4YCg",
            "textDisplay": "2:20 to 2:29.  Well then they SHOULDN'T advertise them as 4k and 144hz in the same ad for the same product.  I'm sick of this false advertising bullshit.",
            "textOriginal": "2:20 to 2:29.  Well then they SHOULDN'T advertise them as 4k and 144hz in the same ad for the same product.  I'm sick of this false advertising bullshit.",
            "authorDisplayName": "Motoryzen",
            "authorProfileImageUrl": "https://yt3.ggpht.com/ytc/AKedOLSkYJB0Ca5kbV_-hQ_et69QUHji6PFWGfYleQ=s48-c-k-c0x00ffffff-no-rj",
            "authorChannelUrl": "http://www.youtube.com/channel/UCfPNNMJniuVKaTp5NMaLGzw",
            "authorChannelId": {
              "value": "UCfPNNMJniuVKaTp5NMaLGzw"
            },
            "canRate": true,
            "viewerRating": "none",
            "likeCount": 0,
            "publishedAt": "2018-06-19T00:32:44Z",
            "updatedAt": "2018-06-19T00:32:44Z"
          }
        },
        "canReply": true,
        "totalReplyCount": 0,
        "isPublic": true
      }
    },
    {
      "kind": "youtube#commentThread",
      "etag": "nUXROt0Zwbwuh3CtPBbjRIMCtco",
      "id": "UgxD1HCkzH-HZLKHdGB4AaABAg",
      "snippet": {
        "videoId": "-bjCeWG4YCg",
        "topLevelComment": {
          "kind": "youtube#comment",
          "etag": "bDonQDYTWHH6T1qdcUFtehSAyog",
          "id": "UgxD1HCkzH-HZLKHdGB4AaABAg",
          "snippet": {
            "videoId": "-bjCeWG4YCg",
            "textDisplay": "That's actually a dick move from AMD.",
            "textOriginal": "That's actually a dick move from AMD.",
            "authorDisplayName": "Avery Tucker",
            "authorProfileImageUrl": "https://yt3.ggpht.com/ytc/AKedOLTm0SwodEaRSDb0lHE23PlBKl0xBHQL0P6_zw=s48-c-k-c0x00ffffff-no-rj",
            "authorChannelUrl": "http://www.youtube.com/channel/UC2b5Y9OvkXgOmTXLnJ0WJzA",
            "authorChannelId": {
              "value": "UC2b5Y9OvkXgOmTXLnJ0WJzA"
            },
            "canRate": true,
            "viewerRating": "none",
            "likeCount": 0,
            "publishedAt": "2018-06-19T00:31:56Z",
            "updatedAt": "2018-06-19T00:31:56Z"
          }
        },
        "canReply": true,
        "totalReplyCount": 0,
        "isPublic": true
      }
    },
    {
      "kind": "youtube#commentThread",
      "etag": "pNCFW7jGT8cZoXT0wVXztqiOF38",
      "id": "UgzlDMmptf8i2OHXzRF4AaABAg",
      "snippet": {
        "videoId": "-bjCeWG4YCg",
        "topLevelComment": {
          "kind": "youtube#comment",
          "etag": "qoys9QDcw6qxoTEECiNm_uhqinE",
          "id": "UgzlDMmptf8i2OHXzRF4AaABAg",
          "snippet": {
            "videoId": "-bjCeWG4YCg",
            "textDisplay": "Cool Linus!!!",
            "textOriginal": "Cool Linus!!!",
            "authorDisplayName": "Deon Spates",
            "authorProfileImageUrl": "https://yt3.ggpht.com/ytc/AKedOLSavx5b_YkyuI8t54ZLYk3yHrZR1GC1V31EKCHmJA=s48-c-k-c0x00ffffff-no-rj",
            "authorChannelUrl": "http://www.youtube.com/channel/UCdjKRMpV50bHtBY9PhQ5GgA",
            "authorChannelId": {
              "value": "UCdjKRMpV50bHtBY9PhQ5GgA"
            },
            "canRate": true,
            "viewerRating": "none",
            "likeCount": 0,
            "publishedAt": "2018-06-19T00:31:41Z",
            "updatedAt": "2018-06-19T00:31:41Z"
          }
        },
        "canReply": true,
        "totalReplyCount": 0,
        "isPublic": true
      }
    },
    {
      "kind": "youtube#commentThread",
      "etag": "duWDhZAxtJn4mt_cyAS__Fr-2ZY",
      "id": "UgwWxa2eGV6vmEkez7V4AaABAg",
      "snippet": {
        "videoId": "-bjCeWG4YCg",
        "topLevelComment": {
          "kind": "youtube#comment",
          "etag": "DgcTLZpGr9VACIJAmatmuWNHqew",
          "id": "UgwWxa2eGV6vmEkez7V4AaABAg",
          "snippet": {
            "videoId": "-bjCeWG4YCg",
            "textDisplay": "woww im super early",
            "textOriginal": "woww im super early",
            "authorDisplayName": "Anggiet Bracmatya",
            "authorProfileImageUrl": "https://yt3.ggpht.com/ytc/AKedOLQHE8ry-ao8mydh7E9ia2uck59Rde5XqgmbmNnJgQ=s48-c-k-c0x00ffffff-no-rj",
            "authorChannelUrl": "http://www.youtube.com/channel/UCu15FdPEH9A-KHQebgpZYSw",
            "authorChannelId": {
              "value": "UCu15FdPEH9A-KHQebgpZYSw"
            },
            "canRate": true,
            "viewerRating": "none",
            "likeCount": 0,
            "publishedAt": "2018-06-19T00:31:41Z",
            "updatedAt": "2018-06-19T00:31:41Z"
          }
        },
        "canReply": true,
        "totalReplyCount": 0,
        "isPublic": true
      }
    },
    {
      "kind": "youtube#commentThread",
      "etag": "uZwAHC06bHxGsCC9kUASr6dtleU",
      "id": "UgxV1PJ4n7zPWIT5ds94AaABAg",
      "snippet": {
        "videoId": "-bjCeWG4YCg",
        "topLevelComment": {
          "kind": "youtube#comment",
          "etag": "heON34N3Zz6hLmxpRbfrND7mvtA",
          "id": "UgxV1PJ4n7zPWIT5ds94AaABAg",
          "snippet": {
            "videoId": "-bjCeWG4YCg",
            "textDisplay": "I miss Riley",
            "textOriginal": "I miss Riley",
            "authorDisplayName": "Jopehaful",
            "authorProfileImageUrl": "https://yt3.ggpht.com/ytc/AKedOLTRT7SOozNj7fH90nTrMBCxDLRLejSmLo9aXQ=s48-c-k-c0x00ffffff-no-rj",
            "authorChannelUrl": "http://www.youtube.com/channel/UCPvmTsGniVBRtR36A3DLsZw",
            "authorChannelId": {
              "value": "UCPvmTsGniVBRtR36A3DLsZw"
            },
            "canRate": true,
            "viewerRating": "none",
            "likeCount": 169,
            "publishedAt": "2018-06-19T00:31:31Z",
            "updatedAt": "2018-06-19T00:31:31Z"
          }
        },
        "canReply": true,
        "totalReplyCount": 7,
        "isPublic": true
      }
    },
    {
      "kind": "youtube#commentThread",
      "etag": "NvuXxxaOT5U6B8MDYmOoG_pZh9M",
      "id": "Ugzu67U8Z-aw95VKj4B4AaABAg",
      "snippet": {
        "videoId": "-bjCeWG4YCg",
        "topLevelComment": {
          "kind": "youtube#comment",
          "etag": "vopoeEYodYZphcJzZIYk-hdyjp0",
          "id": "Ugzu67U8Z-aw95VKj4B4AaABAg",
          "snippet": {
            "videoId": "-bjCeWG4YCg",
            "textDisplay": "Uploaded 1 min ago and already 50 views? It's a 6 min video",
            "textOriginal": "Uploaded 1 min ago and already 50 views? It's a 6 min video",
            "authorDisplayName": "Aaron 572",
            "authorProfileImageUrl": "https://yt3.ggpht.com/ytc/AKedOLRjvCWTuFcTyA7v5cYEJA_8IMTFjoB59P8MGw=s48-c-k-c0x00ffffff-no-rj",
            "authorChannelUrl": "http://www.youtube.com/channel/UCQcsEoIYt0RQKfHqUvech-A",
            "authorChannelId": {
              "value": "UCQcsEoIYt0RQKfHqUvech-A"
            },
            "canRate": true,
            "viewerRating": "none",
            "likeCount": 0,
            "publishedAt": "2018-06-19T00:31:06Z",
            "updatedAt": "2018-06-19T00:31:06Z"
          }
        },
        "canReply": true,
        "totalReplyCount": 0,
        "isPublic": true
      }
    },
    {
      "kind": "youtube#commentThread",
      "etag": "RhEQcQfZoD-4tu4F6kQZOxZiTqs",
      "id": "UgxQ7Fim-doTbgg2GR14AaABAg",
      "snippet": {
        "videoId": "-bjCeWG4YCg",
        "topLevelComment": {
          "kind": "youtube#comment",
          "etag": "jgta4_vH-cphVch7smAqZF0CVRg",
          "id": "UgxQ7Fim-doTbgg2GR14AaABAg",
          "snippet": {
            "videoId": "-bjCeWG4YCg",
            "textDisplay": "Clearly this comment requires some love",
            "textOriginal": "Clearly this comment requires some love",
            "authorDisplayName": "Expectations",
            "authorProfileImageUrl": "https://yt3.ggpht.com/ytc/AKedOLTfobzgEZD4dw3KvwiZmj9fOY5K-JH0b6oJXjBL=s48-c-k-c0x00ffffff-no-rj",
            "authorChannelUrl": "http://www.youtube.com/channel/UCtDAkSujaSZU6akvUx-QWNg",
            "authorChannelId": {
              "value": "UCtDAkSujaSZU6akvUx-QWNg"
            },
            "canRate": true,
            "viewerRating": "none",
            "likeCount": 23,
            "publishedAt": "2018-06-19T00:31:03Z",
            "updatedAt": "2018-06-19T00:31:03Z"
          }
        },
        "canReply": true,
        "totalReplyCount": 2,
        "isPublic": true
      }
    },
    {
      "kind": "youtube#commentThread",
      "etag": "KN52y_XbvdMex5LxqN_h0fQT49E",
      "id": "UgzX3N7ag0rDQCx0wSZ4AaABAg",
      "snippet": {
        "videoId": "-bjCeWG4YCg",
        "topLevelComment": {
          "kind": "youtube#comment",
          "etag": "RCheWODzYgDrH98d0CB7s5W1c5g",
          "id": "UgzX3N7ag0rDQCx0wSZ4AaABAg",
          "snippet": {
            "videoId": "-bjCeWG4YCg",
            "textDisplay": "xxx is ded :(",
            "textOriginal": "xxx is ded :(",
            "authorDisplayName": "Phrasing",
            "authorProfileImageUrl": "https://yt3.ggpht.com/ytc/AKedOLSHwIWbJLCG630_xGxGHlnEXZI4VwFLlVjtVrr45A=s48-c-k-c0x00ffffff-no-rj",
            "authorChannelUrl": "http://www.youtube.com/channel/UCqKUMyPHZZPguE1Hx_YZTdw",
            "authorChannelId": {
              "value": "UCqKUMyPHZZPguE1Hx_YZTdw"
            },
            "canRate": true,
            "viewerRating": "none",
            "likeCount": 0,
            "publishedAt": "2018-06-19T00:30:52Z",
            "updatedAt": "2018-06-19T00:30:52Z"
          }
        },
        "canReply": true,
        "totalReplyCount": 1,
        "isPublic": true
      }
    },
    {
      "kind": "youtube#commentThread",
      "etag": "G3l0W6iY5u-X4ZRO0O2wlQCZG1s",
      "id": "UgzjCYqNcSp6O6SnNT14AaABAg",
      "snippet": {
        "videoId": "-bjCeWG4YCg",
        "topLevelComment": {
          "kind": "youtube#comment",
          "etag": "Mmvm1sWh5wUMIOsdrK8_ZrQ_CS4",
          "id": "UgzjCYqNcSp6O6SnNT14AaABAg",
          "snippet": {
            "videoId": "-bjCeWG4YCg",
            "textDisplay": "Despacito",
            "textOriginal": "Despacito",
            "authorDisplayName": "the guy in Alaska",
            "authorProfileImageUrl": "https://yt3.ggpht.com/ytc/AKedOLQ4SJX5wjeLNu0j0QYve4eH_bT3j0tq7MX56jv4=s48-c-k-c0x00ffffff-no-rj",
            "authorChannelUrl": "http://www.youtube.com/channel/UCCLrq-3a3pbIB9BKdmZl7qQ",
            "authorChannelId": {
              "value": "UCCLrq-3a3pbIB9BKdmZl7qQ"
            },
            "canRate": true,
            "viewerRating": "none",
            "likeCount": 6,
            "publishedAt": "2018-06-19T00:30:52Z",
            "updatedAt": "2018-06-19T00:30:52Z"
          }
        },
        "canReply": true,
        "totalReplyCount": 4,
        "isPublic": true
      }
    },
    {
      "kind": "youtube#commentThread",
      "etag": "u7IbJ90J_oG4dM3JtR-pawp04E8",
      "id": "UgxO3BHabypvwK1S3bl4AaABAg",
      "snippet": {
        "videoId": "-bjCeWG4YCg",
        "topLevelComment": {
          "kind": "youtube#comment",
          "etag": "7ymMbAN478FBxegD9qa3jdVaaYc",
          "id": "UgxO3BHabypvwK1S3bl4AaABAg",
          "snippet": {
            "videoId": "-bjCeWG4YCg",
            "textDisplay": "Hello, great video. Bring back Riley.",
            "textOriginal": "Hello, great video. Bring back Riley.",
            "authorDisplayName": "Brandon Stobie",
            "authorProfileImageUrl": "https://yt3.ggpht.com/ytc/AKedOLQP7i5f9ewQtn6ELyE7BaTE8Bl64v_98odYOC3k=s48-c-k-c0x00ffffff-no-rj",
            "authorChannelUrl": "http://www.youtube.com/channel/UCYuxpo5gRlj6IWMzZoCgulA",
            "authorChannelId": {
              "value": "UCYuxpo5gRlj6IWMzZoCgulA"
            },
            "canRate": true,
            "viewerRating": "none",
            "likeCount": 31,
            "publishedAt": "2018-06-19T00:30:44Z",
            "updatedAt": "2018-06-19T00:31:20Z"
          }
        },
        "canReply": true,
        "totalReplyCount": 2,
        "isPublic": true
      }
    },
    {
      "kind": "youtube#commentThread",
      "etag": "bxJODyAp9fcFcuSyoPKrQw-Ifp4",
      "id": "Ugxl6m5m89bUuDc-3iB4AaABAg",
      "snippet": {
        "videoId": "-bjCeWG4YCg",
        "topLevelComment": {
          "kind": "youtube#comment",
          "etag": "dqwj2TVruVb-AsQoOaHWq75wfA4",
          "id": "Ugxl6m5m89bUuDc-3iB4AaABAg",
          "snippet": {
            "videoId": "-bjCeWG4YCg",
            "textDisplay": "Riley where :'(",
            "textOriginal": "Riley where :'(",
            "authorDisplayName": "TheBaddest",
            "authorProfileImageUrl": "https://yt3.ggpht.com/ytc/AKedOLSwkE4iRhHKCWfSshiubu1JL7cl1fqFw0q6HA=s48-c-k-c0x00ffffff-no-rj",
            "authorChannelUrl": "http://www.youtube.com/channel/UCx7rUoIV-UezZins0MGd0-g",
            "authorChannelId": {
              "value": "UCx7rUoIV-UezZins0MGd0-g"
            },
            "canRate": true,
            "viewerRating": "none",
            "likeCount": 15,
            "publishedAt": "2018-06-19T00:30:32Z",
            "updatedAt": "2018-06-19T00:30:32Z"
          }
        },
        "canReply": true,
        "totalReplyCount": 1,
        "isPublic": true
      }
    },
    {
      "kind": "youtube#commentThread",
      "etag": "z7Q5c19Dmjth_Pat-gkmmCDbtLM",
      "id": "UgydottadjGDKhUGXl14AaABAg",
      "snippet": {
        "videoId": "-bjCeWG4YCg",
        "topLevelComment": {
          "kind": "youtube#comment",
          "etag": "nM-dR6eZRo9d4Z3oyUbYrgpo-v4",
          "id": "UgydottadjGDKhUGXl14AaABAg",
          "snippet": {
            "videoId": "-bjCeWG4YCg",
            "textDisplay": "nope. not first. ;(",
            "textOriginal": "nope. not first. ;(",
            "authorDisplayName": "Expectations",
            "authorProfileImageUrl": "https://yt3.ggpht.com/ytc/AKedOLTfobzgEZD4dw3KvwiZmj9fOY5K-JH0b6oJXjBL=s48-c-k-c0x00ffffff-no-rj",
            "authorChannelUrl": "http://www.youtube.com/channel/UCtDAkSujaSZU6akvUx-QWNg",
            "authorChannelId": {
              "value": "UCtDAkSujaSZU6akvUx-QWNg"
            },
            "canRate": true,
            "viewerRating": "none",
            "likeCount": 1,
            "publishedAt": "2018-06-19T00:30:29Z",
            "updatedAt": "2018-06-19T00:30:40Z"
          }
        },
        "canReply": true,
        "totalReplyCount": 0,
        "isPublic": true
      }
    },
    {
      "kind": "youtube#commentThread",
      "etag": "YH7cLL4j6rzL-ewZj2m6qA02HOg",
      "id": "UgwpO9aSXrMSANPlWu94AaABAg",
      "snippet": {
        "videoId": "-bjCeWG4YCg",
        "topLevelComment": {
          "kind": "youtube#comment",
          "etag": "oD7-QiSHUekn2_4ciXhRyeJa0bI",
          "id": "UgwpO9aSXrMSANPlWu94AaABAg",
          "snippet": {
            "videoId": "-bjCeWG4YCg",
            "textDisplay": "I managed to watch a 6min of video in 1 second just so I could make a useless comment.",
            "textOriginal": "I managed to watch a 6min of video in 1 second just so I could make a useless comment.",
            "authorDisplayName": "Hobbit Stomper",
            "authorProfileImageUrl": "https://yt3.ggpht.com/ytc/AKedOLR38RVyVxfrVQZEPbKNuDGebEQF0yv35DKRkR04=s48-c-k-c0x00ffffff-no-rj",
            "authorChannelUrl": "http://www.youtube.com/channel/UC7N_ctz_usF3AmtxqrZhyCw",
            "authorChannelId": {
              "value": "UC7N_ctz_usF3AmtxqrZhyCw"
            },
            "canRate": true,
            "viewerRating": "none",
            "likeCount": 81,
            "publishedAt": "2018-06-19T00:30:28Z",
            "updatedAt": "2018-06-19T00:30:28Z"
          }
        },
        "canReply": true,
        "totalReplyCount": 1,
        "isPublic": true
      }
    },
    {
      "kind": "youtube#commentThread",
      "etag": "3zMcrgs3bdMzGciqLoVaf9VPhhc",
      "id": "Ugyw5QbAKylYLhL9yQF4AaABAg",
      "snippet": {
        "videoId": "-bjCeWG4YCg",
        "topLevelComment": {
          "kind": "youtube#comment",
          "etag": "YvjhH4l1D8e5C8dKAFV3fPMgcbY",
          "id": "Ugyw5QbAKylYLhL9yQF4AaABAg",
          "snippet": {
            "videoId": "-bjCeWG4YCg",
            "textDisplay": "No one wins these giveaways. Change my mind.",
            "textOriginal": "No one wins these giveaways. Change my mind.",
            "authorDisplayName": "Shoham Chakraborty",
            "authorProfileImageUrl": "https://yt3.ggpht.com/ytc/AKedOLTGOKgfBPmahGejjKCGkbwTZzeVWiIA-GRh3klwww=s48-c-k-c0x00ffffff-no-rj",
            "authorChannelUrl": "http://www.youtube.com/channel/UCTglWq-Qse67NEYslisMZWQ",
            "authorChannelId": {
              "value": "UCTglWq-Qse67NEYslisMZWQ"
            },
            "canRate": true,
            "viewerRating": "none",
            "likeCount": 0,
            "publishedAt": "2018-06-19T00:30:08Z",
            "updatedAt": "2018-06-19T00:30:08Z"
          }
        },
        "canReply": true,
        "totalReplyCount": 0,
        "isPublic": true
      }
    },
    {
      "kind": "youtube#commentThread",
      "etag": "YFb3Y-KMR40p_9ZP8qrXU2Lv4R4",
      "id": "Ugy8JiR_sy57uHTNIPp4AaABAg",
      "snippet": {
        "videoId": "-bjCeWG4YCg",
        "topLevelComment": {
          "kind": "youtube#comment",
          "etag": "5pnthRmCQDZ777PP_eYGwCAl7JU",
          "id": "Ugy8JiR_sy57uHTNIPp4AaABAg",
          "snippet": {
            "videoId": "-bjCeWG4YCg",
            "textDisplay": "First",
            "textOriginal": "First",
            "authorDisplayName": "dababy7",
            "authorProfileImageUrl": "https://yt3.ggpht.com/0RWw6a--NWZwW97ODPVLHTuXnPD8DCImaEqeuOVY61mS47vuu8e2OJ3G1J8y3GcoBi5HfViZ=s48-c-k-c0x00ffffff-no-rj",
            "authorChannelUrl": "http://www.youtube.com/channel/UCnlRF8XXeq8hmuV_zczJPwA",
            "authorChannelId": {
              "value": "UCnlRF8XXeq8hmuV_zczJPwA"
            },
            "canRate": true,
            "viewerRating": "none",
            "likeCount": 0,
            "publishedAt": "2018-06-19T00:29:58Z",
            "updatedAt": "2018-06-19T00:29:58Z"
          }
        },
        "canReply": true,
        "totalReplyCount": 0,
        "isPublic": true
      }
    },
    {
      "kind": "youtube#commentThread",
      "etag": "ihxHWNeXCPrpcodz9640v6vWq34",
      "id": "UgxOKDeka8iurLcQyN94AaABAg",
      "snippet": {
        "videoId": "-bjCeWG4YCg",
        "topLevelComment": {
          "kind": "youtube#comment",
          "etag": "aYCIv8frzgs_Uv9LGaFa-Tn_p2A",
          "id": "UgxOKDeka8iurLcQyN94AaABAg",
          "snippet": {
            "videoId": "-bjCeWG4YCg",
            "textDisplay": "sup fucks",
            "textOriginal": "sup fucks",
            "authorDisplayName": "OS190 190",
            "authorProfileImageUrl": "https://yt3.ggpht.com/ytc/AKedOLQWH1TZFbPBttZEPGwE4vqUZUThaQbU3RsMs8Tt=s48-c-k-c0x00ffffff-no-rj",
            "authorChannelUrl": "http://www.youtube.com/channel/UCz9a6Kq0oyYP1egf2sIq1iA",
            "authorChannelId": {
              "value": "UCz9a6Kq0oyYP1egf2sIq1iA"
            },
            "canRate": true,
            "viewerRating": "none",
            "likeCount": 33,
            "publishedAt": "2018-06-19T00:29:56Z",
            "updatedAt": "2018-06-19T00:29:56Z"
          }
        },
        "canReply": true,
        "totalReplyCount": 8,
        "isPublic": true
      }
    },
    {
      "kind": "youtube#commentThread",
      "etag": "9-xg8R3YMRQwb_A5E26pQXSEy78",
      "id": "UgyseisoASE3vjkAP4F4AaABAg",
      "snippet": {
        "videoId": "-bjCeWG4YCg",
        "topLevelComment": {
          "kind": "youtube#comment",
          "etag": "HdSt05lvIsoMg3fhHpQatSdxvi8",
          "id": "UgyseisoASE3vjkAP4F4AaABAg",
          "snippet": {
            "videoId": "-bjCeWG4YCg",
            "textDisplay": "Nice Video \u003c3",
            "textOriginal": "Nice Video \u003c3",
            "authorDisplayName": "Opaque.",
            "authorProfileImageUrl": "https://yt3.ggpht.com/ytc/AKedOLSGxZ1JrluzWBDMHMs2b_pSuBdV_52VaE1JrH1w9A=s48-c-k-c0x00ffffff-no-rj",
            "authorChannelUrl": "http://www.youtube.com/channel/UCNaoLmisAVQBSkeSA1v_LYA",
            "authorChannelId": {
              "value": "UCNaoLmisAVQBSkeSA1v_LYA"
            },
            "canRate": true,
            "viewerRating": "none",
            "likeCount": 0,
            "publishedAt": "2018-06-19T00:29:52Z",
            "updatedAt": "2018-06-19T00:29:52Z"
          }
        },
        "canReply": true,
        "totalReplyCount": 0,
        "isPublic": true
      }
    },
    {
      "kind": "youtube#commentThread",
      "etag": "MXWjgD6wIPAbnqhV3FMmCGp9r8M",
      "id": "UgyIca5WqfeJAn4CNoV4AaABAg",
      "snippet": {
        "videoId": "-bjCeWG4YCg",
        "topLevelComment": {
          "kind": "youtube#comment",
          "etag": "--032DSsAAZD4yC9iX5rUfi_JkQ",
          "id": "UgyIca5WqfeJAn4CNoV4AaABAg",
          "snippet": {
            "videoId": "-bjCeWG4YCg",
            "textDisplay": "first hehe",
            "textOriginal": "first hehe",
            "authorDisplayName": "OpaxX",
            "authorProfileImageUrl": "https://yt3.ggpht.com/ytc/AKedOLRQFAjQoRCt6JzXMISi2IUp-qiN0EUBpVYdTfdLsw=s48-c-k-c0x00ffffff-no-rj",
            "authorChannelUrl": "http://www.youtube.com/channel/UCRS1LB7q5AtMH1UNcunch8Q",
            "authorChannelId": {
              "value": "UCRS1LB7q5AtMH1UNcunch8Q"
            },
            "canRate": true,
            "viewerRating": "none",
            "likeCount": 0,
            "publishedAt": "2018-06-19T00:29:48Z",
            "updatedAt": "2018-06-19T00:29:48Z"
          }
        },
        "canReply": true,
        "totalReplyCount": 0,
        "isPublic": true
      }
    },
    {
      "kind": "youtube#commentThread",
      "etag": "sV3PA3HS39mc8EEffpTW7Td-cm8",
      "id": "UgyCf6VI3_tBNlj9I454AaABAg",
      "snippet": {
        "videoId": "-bjCeWG4YCg",
        "topLevelComment": {
          "kind": "youtube#comment",
          "etag": "QOIgsFNiP-noOYuFSH2Q01wk7fA",
          "id": "UgyCf6VI3_tBNlj9I454AaABAg",
          "snippet": {
            "videoId": "-bjCeWG4YCg",
            "textDisplay": "Boi",
            "textOriginal": "Boi",
            "authorDisplayName": "Brayden G.",
            "authorProfileImageUrl": "https://yt3.ggpht.com/ytc/AKedOLSBN7NVnt3ND6W4gf6ncyXlIQWaIXMqD0_qQOu_xA=s48-c-k-c0x00ffffff-no-rj",
            "authorChannelUrl": "http://www.youtube.com/channel/UCiJ6MwCY6KeJwi7cjAkjZlg",
            "authorChannelId": {
              "value": "UCiJ6MwCY6KeJwi7cjAkjZlg"
            },
            "canRate": true,
            "viewerRating": "none",
            "likeCount": 5,
            "publishedAt": "2018-06-19T00:29:46Z",
            "updatedAt": "2018-06-19T00:29:46Z"
          }
        },
        "canReply": true,
        "totalReplyCount": 1,
        "isPublic": true
      }
    }
  ]
}
